orthogpoly/__init__.py
orthogpoly/helpers.py
orthogpoly/c1/__init__.py
orthogpoly/c1/associated_legendre.py
orthogpoly/c1/chebyshev1.py
orthogpoly/c1/chebyshev2.py
orthogpoly/c1/gegenbauer.py
orthogpoly/c1/jacobi.py
orthogpoly/c1/legendre.py
orthogpoly/c1/tools.py
orthogpoly/cn/__init__.py
orthogpoly/cn/main.py
orthogpoly/cn/tools.py
orthogpoly/e1r/__init__.py
orthogpoly/e1r/main.py
orthogpoly/e1r/tools.py
orthogpoly/e1r2/__init__.py
orthogpoly/e1r2/main.py
orthogpoly/e1r2/tools.py
orthogpoly/enr2/__init__.py
orthogpoly/enr2/main.py
orthogpoly/enr2/tools.py
orthogpoly/s2/__init__.py
orthogpoly/s2/tools.py
orthogpoly/s2/xu.py
orthogpoly/s2/zernike.py
orthogpoly/s2/zernike2.py
orthogpoly/t2/__init__.py
orthogpoly/t2/main.py
orthogpoly/t2/tools.py
orthogpoly/tools/__init__.py
orthogpoly/tools/generate_rc.py
orthogpoly/u3/__init__.py
orthogpoly/u3/main.py
orthogpoly/u3/tools.py
orthogpoly-0.9.5.dist-info/LICENSE
orthogpoly-0.9.5.dist-info/METADATA
orthogpoly-0.9.5.dist-info/WHEEL
orthogpoly-0.9.5.dist-info/top_level.txt
orthogpoly-0.9.5.dist-info/RECORD
